.hgignore
.hgtags
ABOUT.txt
CHANGES.txt
COPYRIGHT.txt
LICENSE.txt
README.txt
base.cfg
index.txt
setup.py
doc/about.txt
doc/conf.py
doc/modules.txt
doc/tests.txt
tl/__init__.py
tl.gcrop.egg-info/PKG-INFO
tl.gcrop.egg-info/SOURCES.txt
tl.gcrop.egg-info/dependency_links.txt
tl.gcrop.egg-info/entry_points.txt
tl.gcrop.egg-info/namespace_packages.txt
tl.gcrop.egg-info/not-zip-safe
tl.gcrop.egg-info/requires.txt
tl.gcrop.egg-info/top_level.txt
tl/gcrop/__init__.py
tl/gcrop/app.py
tl/gcrop/cropping.py
tl/gcrop/edit.py
tl/gcrop/tests.py