Metadata-Version: 1.0
Name: tl.gcrop
Version: 0.1
Summary: Visually crop an image under various constraints.
Home-page: http://packages.python.org/tl.gcrop/
Author: Thomas Lotze
Author-email: thomas@thomas-lotze.de
License: ZPL 2.1
Keywords: gtk visual crop image are constraints interactive aspect ratio
Platform: UNKNOWN
Classifier: Development Status :: 3 - Alpha
Classifier:     Environment :: X11 Applications
Classifier:     Environment :: X11 Applications :: GTK
Classifier:     Intended Audience :: End Users/Desktop
Classifier:     License :: OSI Approved :: Zope Public License
Classifier:     Programming Language :: Python
Classifier:     Topic :: Utilities
